telecom_channel_log/__init__.py
telecom_channel_log/i telecom_channel_log.py
telecom_channel_log-1.2.dist-info/LICENSE
telecom_channel_log-1.2.dist-info/METADATA
telecom_channel_log-1.2.dist-info/WHEEL
telecom_channel_log-1.2.dist-info/top_level.txt
telecom_channel_log-1.2.dist-info/RECORD
