Metadata-Version: 2.2
Name: telecom_channel_log
Version: 1.2
Summary: 专为电渠应用服务设计的高效日志库，支持多级别日志记录、日志轮转、流水日志追踪及埋点日 志功能，深度集成 Flask 和 Requests 框架。
Author: Unnamed great master
Author-email: <gqylpy@outlook.com>
License: MIT
Project-URL: Source, https://github.com/2018-11-27/telecom-channel-log
Classifier: Development Status :: 3 - Alpha
Classifier: Intended Audience :: Developers
Classifier: License :: OSI Approved :: Apache Software License
Classifier: Natural Language :: Chinese (Simplified)
Classifier: Natural Language :: English
Classifier: Operating System :: OS Independent
Classifier: Topic :: Software Development :: Libraries :: Python Modules
Classifier: Topic :: Artistic Software
Classifier: Topic :: Internet :: Log Analysis
Classifier: Topic :: Text Processing
Classifier: Programming Language :: Python :: 2.7
Classifier: Programming Language :: Python :: 3.0
Classifier: Programming Language :: Python :: 3.1
Classifier: Programming Language :: Python :: 3.2
Classifier: Programming Language :: Python :: 3.3
Classifier: Programming Language :: Python :: 3.4
Classifier: Programming Language :: Python :: 3.5
Classifier: Programming Language :: Python :: 3.6
Classifier: Programming Language :: Python :: 3.7
Classifier: Programming Language :: Python :: 3.8
Classifier: Programming Language :: Python :: 3.9
Classifier: Programming Language :: Python :: 3.10
Classifier: Programming Language :: Python :: 3.11
Classifier: Programming Language :: Python :: 3.12
Classifier: Programming Language :: Python :: 3.13
Requires-Python: >=2.7
License-File: LICENSE
Requires-Dist: gqylpy_log==0.0a1
Provides-Extra: flask
Requires-Dist: Flask>=0.10; extra == "flask"
Provides-Extra: requests
Requires-Dist: requests>=2.19; extra == "requests"
Dynamic: author
Dynamic: author-email
Dynamic: classifier
Dynamic: description
Dynamic: description-content-type
Dynamic: license
Dynamic: project-url
Dynamic: provides-extra
Dynamic: requires-dist
Dynamic: requires-python
Dynamic: summary
